src/__init__.py
src/app.py
src/lint.py
python_qualiter-0.57.0.dist-info/LICENSE
python_qualiter-0.57.0.dist-info/METADATA
python_qualiter-0.57.0.dist-info/WHEEL
python_qualiter-0.57.0.dist-info/entry_points.txt
python_qualiter-0.57.0.dist-info/RECORD
