Metadata-Version: 2.3
Name: python-qualiter
Version: 0.57.0
Summary: A modern Click-based CLI tool for running multiple linting tools on Python files with a clean visual output.
License: MIT
Author: Radovan Bacovic
Author-email: radovan.bacovic@gmail.com
Requires-Python: >=3.9
Classifier: License :: OSI Approved :: MIT License
Classifier: Operating System :: OS Independent
Classifier: Programming Language :: Python :: 3
Classifier: Programming Language :: Python :: 3.9
Classifier: Programming Language :: Python :: 3.10
Classifier: Programming Language :: Python :: 3.11
Classifier: Programming Language :: Python :: 3.12
Classifier: Programming Language :: Python :: 3.13
Classifier: Programming Language :: Python :: 3.6
Classifier: Programming Language :: Python :: 3.7
Classifier: Programming Language :: Python :: 3.8
Requires-Dist: black (==22.6.0)
Requires-Dist: click (>=8.0.0,<9.0.0)
Requires-Dist: flake8 (>=4.0.0,<5.0.0)
Requires-Dist: isort (>=5.10.0,<6.0.0)
Requires-Dist: mypy (>=0.950,<0.951)
Requires-Dist: pathspec (>=0.9.0,<0.10.0)
Requires-Dist: platformdirs (>=2.0.0,<3.0.0)
Requires-Dist: pylint (>=2.12.0,<3.0.0)
Requires-Dist: pytest (>=8.3.5,<9.0.0)
Requires-Dist: ruff (>=0.1.0,<0.2.0)
Requires-Dist: tomli (>=1.1.0,<2.0.0) ; python_version >= "3.6" and python_version < "4.0"
Requires-Dist: typing-extensions (>=4.0.0,<5.0.0)
Requires-Dist: vulture (>=2.3,<3.0)
Project-URL: Homepage, https://gitlab.com/rbacovic/python-qualiter
Project-URL: Repository, https://gitlab.com/rbacovic/python-qualiter
